{"annotation": {"folder": "train", "filename": "20210128_155618_Burst13.jpg", "path": "c:\\Users\\markc\\Documents\\Vision Stuff\\Tensorflow\\workspace\\training_demo\\images\\train\\20210128_155618_Burst13.jpg", "source": {"database": "Unknown"}, "size": {"width": "1920", "height": "1080", "depth": "3"}, "segmented": "0", "object": [{"name": "basketball", "pose": "Unspecified", "truncated": "0", "difficult": "0", "bndbox": {"xmin": "1343", "ymin": "502", "xmax": "1555", "ymax": "739"}}, {"name": "boulder", "pose": "Unspecified", "truncated": "0", "difficult": "0", "bndbox": {"xmin": "780", "ymin": "319", "xmax": "962", "ymax": "502"}}, {"name": "powercell", "pose": "Unspecified", "truncated": "1", "difficult": "0", "bndbox": {"xmin": "1085", "ymin": "1", "xmax": "1225", "ymax": "217"}}, {"name": "powercell", "pose": "Unspecified", "truncated": "0", "difficult": "0", "bndbox": {"xmin": "961", "ymin": "337", "xmax": "1108", "ymax": "515"}}, {"name": "powercell", "pose": "Unspecified", "truncated": "0", "difficult": "0", "bndbox": {"xmin": "796", "ymin": "498", "xmax": "941", "ymax": "617"}}, {"name": "powercell", "pose": "Unspecified", "truncated": "0", "difficult": "0", "bndbox": {"xmin": "945", "ymin": "508", "xmax": "1104", "ymax": "645"}}, {"name": "powercell", "pose": "Unspecified", "truncated": "0", "difficult": "0", "bndbox": {"xmin": "870", "ymin": "570", "xmax": "994", "ymax": "710"}}, {"name": "powercell", "pose": "Unspecified", "truncated": "0", "difficult": "0", "bndbox": {"xmin": "1121", "ymin": "596", "xmax": "1282", "ymax": "790"}}, {"name": "powercell", "pose": "Unspecified", "truncated": "0", "difficult": "0", "bndbox": {"xmin": "992", "ymin": "641", "xmax": "1125", "ymax": "794"}}, {"name": "fuel", "pose": "Unspecified", "truncated": "0", "difficult": "0", "bndbox": {"xmin": "1094", "ymin": "888", "xmax": "1231", "ymax": "1027"}}]}}