{"annotation": {"folder": "train", "filename": "20210128_154827_Burst02.jpg", "path": "c:\\Users\\markc\\Documents\\Vision Stuff\\Tensorflow\\workspace\\training_demo\\images\\train\\20210128_154827_Burst02.jpg", "source": {"database": "Unknown"}, "size": {"width": "1920", "height": "1080", "depth": "3"}, "segmented": "0", "object": [{"name": "powercell", "pose": "Unspecified", "truncated": "0", "difficult": "0", "bndbox": {"xmin": "1233", "ymin": "198", "xmax": "1419", "ymax": "388"}}, {"name": "powercell", "pose": "Unspecified", "truncated": "0", "difficult": "0", "bndbox": {"xmin": "837", "ymin": "370", "xmax": "931", "ymax": "474"}}, {"name": "powercell", "pose": "Unspecified", "truncated": "0", "difficult": "0", "bndbox": {"xmin": "929", "ymin": "374", "xmax": "1021", "ymax": "478"}}, {"name": "powercell", "pose": "Unspecified", "truncated": "0", "difficult": "0", "bndbox": {"xmin": "884", "ymin": "543", "xmax": "972", "ymax": "637"}}, {"name": "powercell", "pose": "Unspecified", "truncated": "0", "difficult": "0", "bndbox": {"xmin": "702", "ymin": "423", "xmax": "778", "ymax": "494"}}, {"name": "boulder", "pose": "Unspecified", "truncated": "0", "difficult": "0", "bndbox": {"xmin": "1121", "ymin": "470", "xmax": "1282", "ymax": "631"}}]}}