{"annotation": {"folder": "train", "filename": "20210128_154502_Burst30.jpg", "path": "c:\\Users\\markc\\Documents\\Vision Stuff\\Tensorflow\\workspace\\training_demo\\images\\train\\20210128_154502_Burst30.jpg", "source": {"database": "Unknown"}, "size": {"width": "1920", "height": "1080", "depth": "3"}, "segmented": "0", "object": [{"name": "powercell", "pose": "Unspecified", "truncated": "0", "difficult": "0", "bndbox": {"xmin": "835", "ymin": "345", "xmax": "931", "ymax": "449"}}, {"name": "powercell", "pose": "Unspecified", "truncated": "0", "difficult": "0", "bndbox": {"xmin": "1000", "ymin": "568", "xmax": "1145", "ymax": "688"}}, {"name": "fuel", "pose": "Unspecified", "truncated": "0", "difficult": "0", "bndbox": {"xmin": "937", "ymin": "465", "xmax": "1017", "ymax": "553"}}, {"name": "boulder", "pose": "Unspecified", "truncated": "0", "difficult": "0", "bndbox": {"xmin": "992", "ymin": "323", "xmax": "1145", "ymax": "486"}}]}}