{"annotation": {"folder": "29-31", "filename": "20210130_112341_Burst38.jpg", "path": "c:\\Users\\markc\\Documents\\Vision Stuff\\Tensorflow\\workspace\\training_demo\\images\\20210130_112341_Burst38.jpg", "source": {"database": "Unknown"}, "size": {"width": "3264", "height": "1836", "depth": "3"}, "segmented": "0", "object": [{"name": "powercell", "pose": "Unspecified", "truncated": "0", "difficult": "0", "bndbox": {"xmin": "1494", "ymin": "704", "xmax": "1687", "ymax": "917"}}, {"name": "powercell", "pose": "Unspecified", "truncated": "0", "difficult": "0", "bndbox": {"xmin": "1757", "ymin": "407", "xmax": "1950", "ymax": "577"}}, {"name": "powercell", "pose": "Unspecified", "truncated": "0", "difficult": "0", "bndbox": {"xmin": "2240", "ymin": "447", "xmax": "2414", "ymax": "661"}}]}}